COPYING
MANIFEST.in
README.rst
buildout.cfg
develop.cfg
requirements.txt
setup.py
version.txt
bob/__init__.py
bob.db.voxforge.egg-info/PKG-INFO
bob.db.voxforge.egg-info/SOURCES.txt
bob.db.voxforge.egg-info/dependency_links.txt
bob.db.voxforge.egg-info/entry_points.txt
bob.db.voxforge.egg-info/not-zip-safe
bob.db.voxforge.egg-info/requires.txt
bob.db.voxforge.egg-info/top_level.txt
bob/db/__init__.py
bob/db/voxforge/__init__.py
bob/db/voxforge/config.py
bob/db/voxforge/download_and_untar.py
bob/db/voxforge/driver.py
bob/db/voxforge/query.py
bob/db/voxforge/test.py
bob/db/voxforge/lists/list_of_tgz_files.lst
bob/db/voxforge/lists/dev/for_models.lst
bob/db/voxforge/lists/dev/for_probes.lst
bob/db/voxforge/lists/eval/for_models.lst
bob/db/voxforge/lists/eval/for_probes.lst
bob/db/voxforge/lists/norm/train_optional_world_1.lst
bob/db/voxforge/lists/norm/train_optional_world_2.lst
bob/db/voxforge/lists/norm/train_world.lst
doc/conf.py
doc/guide.rst
doc/index.rst
doc/py_api.rst