Metadata-Version: 1.1
Name: bob.db.voxforge
Version: 2.3.1
Summary: Speaker verification protocol on a subset of the VoxForge database
Home-page: http://gitlab.idiap.ch/bob/bob.db.voxforge
Author: Elie Khoury
Author-email: Elie.Khoury@idiap.ch
License: BSD
Keywords: Speaker Recognition,Speaker verification,Audio processing,Database,Voxforge
Platform: UNKNOWN
Classifier: Framework :: Bob
Classifier: Development Status :: 4 - Beta
Classifier: Intended Audience :: Education
Classifier: License :: OSI Approved :: BSD License
Classifier: Natural Language :: English
Classifier: Programming Language :: Python
Classifier: Programming Language :: Python :: 3
Classifier: Topic :: Scientific/Engineering :: Artificial Intelligence
Classifier: Topic :: Database :: Front-Ends
